{
  "convertable" : true,
  "jps"         : "https://raw.githubusercontent.com/dimkadt/wildfly/master/addons/auto-clustering/auto-cluster.jps",  
  "defaultState": false,
  "compatibleAddons": ["wildfly-cluster"],
  "nodeGroupData": {
    "skipNodeEmails": true,
    "scalingMode": "STATEFUL",
    "adminUrl": "",
    "isResetServicePassword": false
  },
  "description" : "WildFly in Domain Mode with enabled clustering to get HA and session replication among the nodes to guarantee the availability of a deployed Java EE application in case of a node failure. <a href='https://bit.ly/2q6ta3V'>Learn More</a><img width='290' height='157' src='https://bit.ly/2JazyjA'>",
  "skipOnEnvInstall": true
}
